UTIR_Lib/ModuleNode.py
UTIR_Lib/__init__.py
UTIR_Lib-0.0.3.dist-info/METADATA
UTIR_Lib-0.0.3.dist-info/WHEEL
UTIR_Lib-0.0.3.dist-info/top_level.txt
UTIR_Lib-0.0.3.dist-info/RECORD
