Metadata-Version: 2.1
Name: UTIR_Lib
Version: 0.0.3
Summary: Libraries for UTIR
Home-page: https://github.com/pypa/sampleproject
Author: YcMoon
Author-email: mycm1302@hanyang.ac.kr
License: UNKNOWN
Platform: UNKNOWN
Classifier: Programming Language :: Python :: 3
Classifier: License :: OSI Approved :: MIT License
Classifier: Operating System :: OS Independent
Requires-Python: >=3.6
